pymsd/__init__.py
pymsd/easy.py
pymsd/numpy.py
pymsd/pandas.py
pymsd/polars.py
pymsd/proto/__init__.py
pymsd/proto/dataframe_pb2.py
pymsd/proto/msd_pb2.py
pymsd/proto/msd_pb2_grpc.py
pymsd/proto/schema_pb2.py
pymsd/pyarrow.py
pymsd/setting.py
pymsd-0.2.2.dist-info/WHEEL
pymsd-0.2.2.dist-info/METADATA
pymsd-0.2.2.dist-info/RECORD
