Metadata-Version: 2.1
Name: pymsd
Version: 0.2.2
Summary: the python sdk of msd-rs
Home-page: https://github.com/msd-rs/msd-sdk-python
Author: LiJia
Author-email: lijia.c@gmail.com
Requires-Python: >=3.8,<4.0
Classifier: Programming Language :: Python :: 3
Classifier: Programming Language :: Python :: 3.10
Classifier: Programming Language :: Python :: 3.8
Classifier: Programming Language :: Python :: 3.9
Requires-Dist: grpcio (>=1,<2)
Requires-Dist: numpy (>=1,<2)
Requires-Dist: protobuf (>=4,<5)
Project-URL: Repository, https://github.com/msd-rs/msd-sdk-python
